pys3server/__init__.py
pys3server/base_interface.py
pys3server/bucket.py
pys3server/errors.py
pys3server/etag_stream.py
pys3server/interfaces/__init__.py
pys3server/interfaces/file_interface.py
pys3server/jwt_msgpack.py
pys3server/object.py
pys3server/responses.py
pys3server/server.py
pys3server/signature_v4.py
pys3server/upload_part.py
pys3server/utils.py
pys3server/xml_utils.py
pys3server-0.1.0b9.dist-info/LICENSE
pys3server-0.1.0b9.dist-info/METADATA
pys3server-0.1.0b9.dist-info/WHEEL
pys3server-0.1.0b9.dist-info/RECORD
